shelxfile/__init__.py
shelxfile/version.py
shelxfile/atoms/__init__.py
shelxfile/atoms/atom.py
shelxfile/atoms/atoms.py
shelxfile/atoms/pairs.py
shelxfile/atoms/atomic_weights/LICENSE
shelxfile/atoms/atomic_weights/README.md
shelxfile/atoms/atomic_weights/atomicWeightsDecimal.py
shelxfile/cif/cif_template.tmpl
shelxfile/cif/cif_write.py
shelxfile/draw/__init__.py
shelxfile/draw/draw_molecule.py
shelxfile/fit/LICENSE.txt
shelxfile/fit/__init__.py
shelxfile/fit/quatfit.py
shelxfile/misc/__init__.py
shelxfile/misc/dsrmath.py
shelxfile/misc/elements.py
shelxfile/misc/misc.py
shelxfile/refine/__init__.py
shelxfile/refine/refine.py
shelxfile/shelx/__init__.py
shelxfile/shelx/cards.py
shelxfile/shelx/sdm.py
shelxfile/shelx/shelx.py
shelxfile/shelx/symm_cards.py
shelxfile-22.dist-info/METADATA
shelxfile-22.dist-info/WHEEL
shelxfile-22.dist-info/licenses/LICENSE.md
shelxfile-22.dist-info/RECORD
