Metadata-Version: 2.4
Name: shelxfile
Version: 22
Summary: A parser for SHELXL results files
Project-URL: Homepage, https://dkratzert.de/shelxfile.html
Project-URL: Bug Tracker, https://github.com/dkratzert/ShelXFile/issues
Author-email: Daniel Kratzert <dkratzert@gmx.de>
License-File: LICENSE.md
Classifier: Development Status :: 5 - Production/Stable
Classifier: License :: OSI Approved :: MIT License
Classifier: Operating System :: OS Independent
Classifier: Programming Language :: Python :: 3
Classifier: Topic :: Scientific/Engineering :: Chemistry
Requires-Python: >=3.9
